annea_foo/__init__.py
annea_foo/example.py
annea_foo-0.1.63.dist-info/METADATA
annea_foo-0.1.63.dist-info/WHEEL
annea_foo-0.1.63.dist-info/top_level.txt
annea_foo-0.1.63.dist-info/RECORD
